flasktts/__init__.py
flasktts/_utils.py
flasktts/secret.py
flasktts/server.py
flasktts/text_to_speech.py
flasktts/_constants/__init__.py
flasktts/_constants/constants.py
flasktts/_constants/keys.py
flasktts-0.0.9.dist-info/METADATA
flasktts-0.0.9.dist-info/WHEEL
flasktts-0.0.9.dist-info/top_level.txt
flasktts-0.0.9.dist-info/RECORD
