Metadata-Version: 2.1
Name: flasktts
Version: 0.0.9
Summary: flasktts
Home-page: https://github.com/kkristof200/py_flask_tts
Author: Kristof
Classifier: Programming Language :: Python :: 3
Classifier: License :: OSI Approved :: MIT License
Classifier: Operating System :: OS Independent
Requires-Python: >=3.5
Requires-Dist: fastpunct (>=2.0.2)
Requires-Dist: Flask (>=1.1.2)
Requires-Dist: kcu (>=0.0.73)
Requires-Dist: kffmpeg (>=0.2.46)
Requires-Dist: pyttsx3 (>=2.90)
Requires-Dist: setuptools (>=62.3.2)
Requires-Dist: Unidecode (>=1.3.2)
